{
  "source_url": "https://cap.rcpet.edu.tw/exam/115/115exam.html",
  "resources": [
    {
      "text": "參考答案",
      "url": "https://drive.google.com/file/d/1fxfOLQPMdCEMSuziD1qsQZg3vVOGt8df/view?usp=drive_link",
      "type": "pdf",
      "title": "另開新視窗"
    },
    {
      "text": "試題說明",
      "url": "https://drive.google.com/file/d/1uCImBYbMxkme8DxV2Wj5RdxBnNgTeD5n/view?usp=drive_link",
      "type": "pdf",
      "title": "另開新視窗"
    },
    {
      "text": "寫作測驗",
      "url": "https://drive.google.com/file/d/1NceEHPUXT0fZo6UgdCuSdGApQ4embM0t/view?usp=drive_link",
      "type": "pdf",
      "title": "另開新視窗"
    },
    {
      "text": "國文科",
      "url": "https://drive.google.com/file/d/1FQtq4_a4GTsTKURdzPhDkKmONKRXtTJ9/view?usp=drive_link",
      "type": "pdf",
      "title": "另開新視窗"
    },
    {
      "text": "英語（閱讀）",
      "url": "https://drive.google.com/file/d/1pzRZpkZEBg4x7GNTAIrdfGJCxNSKgok-/view?usp=drive_link",
      "type": "pdf",
      "title": "另開新視窗"
    },
    {
      "text": "英語（聽力）",
      "url": "https://drive.google.com/file/d/1zRjsoyQhLRJfmmHtBJfi5qJa6ND1uVJ6/view?usp=drive_link",
      "type": "pdf",
      "title": "另開新視窗"
    },
    {
      "text": "數學科",
      "url": "https://drive.google.com/file/d/1G-grfVw1NldMD3TRG-7Lco-yOuaoTKoK/view?usp=drive_link",
      "type": "pdf",
      "title": "另開新視窗"
    },
    {
      "text": "社會科",
      "url": "https://drive.google.com/file/d/1ITxBlFhNSIbg1u1C7FrU2ODk951wt-RT/view?usp=drive_link",
      "type": "pdf",
      "title": "另開新視窗"
    },
    {
      "text": "自然科",
      "url": "https://drive.google.com/file/d/1ZJNPG9Wz3zuI8UkPGUY50URejxxZYmQ8/view?usp=drive_link",
      "type": "pdf",
      "title": "另開新視窗"
    },
    {
      "text": "「115年國中教育會考試題疑義釋復申請表」",
      "url": "https://cap.rcpet.edu.tw/documents/115年國中教育會考試題疑義釋復申請表.pdf",
      "type": "pdf",
      "title": null
    },
    {
      "text": "學生問卷",
      "url": "https://forms.cloud.microsoft/r/jMi2vkhJbB",
      "type": "link",
      "title": null
    },
    {
      "text": "教師問卷",
      "url": "https://cap.rcpet.edu.tw/survey/index.html",
      "type": "link",
      "title": null
    }
  ]
}